[
  {
    "id": 1,
    "name": "person_4770",
    "coordinates": {
      "x": 4770,
      "y": 4770
    },
    "creationDate": {
      "dateTime": {
        "date": {
          "year": 2025,
          "month": 3,
          "day": 23
        },
        "time": {
          "hour": 11,
          "minute": 53,
          "second": 49,
          "nano": 550490600
        }
      },
      "offset": {
        "totalSeconds": 10800
      },
      "zone": {
        "id": "Europe/Moscow"
      }
    },
    "height": 4770.0,
    "eyeColor": "BLUE",
    "hairColor": "WHITE",
    "nationality": "FRANCE",
    "location": {
      "x": 4770.0,
      "y": 4770,
      "z": 4770,
      "name": "location_4770"
    }
  },
  {
    "id": 2,
    "name": "fghj",
    "coordinates": {
      "x": 876543,
      "y": 34567890
    },
    "creationDate": {
      "dateTime": {
        "date": {
          "year": 2025,
          "month": 3,
          "day": 23
        },
        "time": {
          "hour": 11,
          "minute": 53,
          "second": 49,
          "nano": 550490600
        }
      },
      "offset": {
        "totalSeconds": 10800
      },
      "zone": {
        "id": "Europe/Moscow"
      }
    },
    "height": 1.0E31,
    "eyeColor": "GREEN",
    "hairColor": "GREEN",
    "nationality": "SPAIN",
    "location": {
      "x": 7777.0,
      "y": 45678,
      "z": 3456789,
      "name": "erghjkl"
    }
  },
  {
    "id": 3,
    "name": "person_7983",
    "coordinates": {
      "x": 93112,
      "y": 93112
    },
    "creationDate": {
      "dateTime": {
        "date": {
          "year": 2025,
          "month": 3,
          "day": 23
        },
        "time": {
          "hour": 11,
          "minute": 53,
          "second": 49,
          "nano": 549493900
        }
      },
      "offset": {
        "totalSeconds": 10800
      },
      "zone": {
        "id": "Europe/Moscow"
      }
    },
    "height": 93112.0,
    "eyeColor": "BLUE",
    "hairColor": "WHITE",
    "nationality": "FRANCE",
    "location": {
      "x": 93112.0,
      "y": 93112,
      "z": 93112,
      "name": "location_93112"
    }
  }
]